COPYING
COPYING.lesser
MANIFEST.in
NOTICE
README.md
requirements.txt
setup.cfg
setup.py
compiler/__init__.py
compiler/api/__init__.py
compiler/api/compiler.py
compiler/api/source/auth_key.tl
compiler/api/source/main_api.tl
compiler/api/source/sys_msgs.tl
compiler/api/template/combinator.txt
compiler/api/template/type.txt
compiler/docs/__init__.py
compiler/docs/compiler.py
compiler/docs/template/page.txt
compiler/docs/template/toctree.txt
compiler/errors/__init__.py
compiler/errors/compiler.py
compiler/errors/sort.py
compiler/errors/source/303_SEE_OTHER.tsv
compiler/errors/source/400_BAD_REQUEST.tsv
compiler/errors/source/401_UNAUTHORIZED.tsv
compiler/errors/source/403_FORBIDDEN.tsv
compiler/errors/source/406_NOT_ACCEPTABLE.tsv
compiler/errors/source/420_FLOOD.tsv
compiler/errors/source/500_INTERNAL_SERVER_ERROR.tsv
compiler/errors/source/503_SERVICE_UNAVAILABLE.tsv
compiler/errors/template/class.txt
compiler/errors/template/sub_class.txt
pyrogram1/__init__.py
pyrogram1/client.py
pyrogram1/dispatcher.py
pyrogram1/emoji.py
pyrogram1/file_id.py
pyrogram1/filters.py
pyrogram1/mime_types.py
pyrogram1/py.typed
pyrogram1/scaffold.py
pyrogram1/sync.py
pyrogram1/syncer.py
pyrogram1/utils.py
pyrogram1.egg-info/PKG-INFO
pyrogram1.egg-info/SOURCES.txt
pyrogram1.egg-info/dependency_links.txt
pyrogram1.egg-info/not-zip-safe
pyrogram1.egg-info/requires.txt
pyrogram1.egg-info/top_level.txt
pyrogram1/connection/__init__.py
pyrogram1/connection/connection.py
pyrogram1/connection/transport/__init__.py
pyrogram1/connection/transport/tcp/__init__.py
pyrogram1/connection/transport/tcp/tcp.py
pyrogram1/connection/transport/tcp/tcp_abridged.py
pyrogram1/connection/transport/tcp/tcp_abridged_o.py
pyrogram1/connection/transport/tcp/tcp_full.py
pyrogram1/connection/transport/tcp/tcp_intermediate.py
pyrogram1/connection/transport/tcp/tcp_intermediate_o.py
pyrogram1/crypto/__init__.py
pyrogram1/crypto/aes.py
pyrogram1/crypto/mtproto.py
pyrogram1/crypto/prime.py
pyrogram1/crypto/rsa.py
pyrogram1/errors/__init__.py
pyrogram1/errors/rpc_error.py
pyrogram1/handlers/__init__.py
pyrogram1/handlers/callback_query_handler.py
pyrogram1/handlers/chat_join_request_handler.py
